{
	"authors": {
		"12 elements of great managing": "Rodd Wagner, James K. Harter",
		"50 things you should know about the first world war": "Jim Eldridge",
		"a history of murphys law": "Nick T. Spark",
		"a short history of nearly everything": "Bill Bryson",
		"all the winniethepooh books": "A. A. Milne, Ernest H. Shepard",
		"an exaltation of larks": "James Lipton",
		"antifragile": "Nassim Nicholas Taleb",
		"atomic habits": "James Clear",
		"autobiography of a yogi": "Paramahansa Yogananda",
		"behave the biology of humans at our best and worst": "Robert Sapolsky",
		"blowing the bloody doors off and other lessons in life": "Michael Caine",
		"born to run": "Christopher McDougall",
		"brain training for runners": "Matt Fitzgerald",
		"chris andersons the long tail why the future of business is selling less of more": "Chris Anderson",
		"cognitive surplus": "Clay Shirky",
		"conduct risk management a behavioural approach": "Roger Miles",
		"creativity flow and the psychology of discovery and invention": "Mihaly Csikszentmihalyi",
		"cubed the puzzle of us all": "Ernő Rubik",
		"dare to lead": "Brené Brown",
		"deep work": "Cal Newport",
		"discovering sea shells": "Barry Charles",
		"dont make me think": "Steve Krug",
		"dont think of an elephant": "George Lakoff",
		"drive": "Daniel H. Pink",
		"eat that frog": "Brian Tracy",
		"einsteins mirror": "Tony Hey, Patrick Walters",
		"envisioning information": "Edward R. Tufte",
		"escher bach an eternal golden braid": "Douglas R. Hofstadter",
		"exactly how precision engineers created the modern world": "Simon Winchester",
		"factfulness": "Hans Rosling",
		"feynman lectures on computation": "Tony Hey, Richard P. Feynman",
		"flow the psychology of happiness": "Mihalyi Csikszentmihalyi",
		"food rules": "Michael Pollan",
		"good to go decarbonising travel after the pandemic": "David Metz",
		"greenlights": "Matthew McConaughey",
		"how to absurd scientific advice for common realworld problems": "Randall Munroe",
		"how to change": "Katy Milkman",
		"how to lie with statistics": "Darrell Huff",
		"how to win friends and influence people": "Dale Carnegie",
		"human kind a hopeful history": "Rutger Bregman",
		"if this isnt nice what is the graduation speeches and other words to live": "Kurt Vonnegut",
		"if you want to write": "Brenda Ueland",
		"illustrated norse myths": "Alex Frith",
		"improv wisdom": "Patricia Ryan Madson",
		"invisible women": "Caroline Criado Perez",
		"it doesnt have to be crazy at work": "Jason Fried, David Heinemeier Hansson",
		"jaron lanier": "Jaron Lanier",
		"justice": "Michael J. Sandel",
		"lateral thinking": "Edward de Bono",
		"leaders make the future": "Bob Johansen",
		"leonardo da vinci the graphic works": "Frank Zöllner, Johannes Nathan",
		"lets make sushi": "Andy Matsuda",
		"local": "Alastair Humphreys",
		"loserthink": "Scott Adams",
		"made to stick": "Chip Heath, Dan Heath",
		"managing oneself": "Peter F. Drucker",
		"marie kondo": "Marie Kondo",
		"marvellous maps": "Simon Kuestenmacher",
		"measure what matters": "Doerr John",
		"messy": "Tim Harford",
		"metaphors we live by": "George Lakoff",
		"mind children": "Hans Moravec",
		"more work for mother": "Ruth Schwartz Cowan",
		"my first summer in the sierra": "John Muir",
		"my name is charles saatchi and i am an artoholic": "Charles Saatchi",
		"not the end of the world": "Hannah Ritchie",
		"novak djokovics serve to win": "Novak Djokovic",
		"on writing well": "William Zinsser",
		"one man and his bike": "Mike Carter",
		"philosophy in the flesh": "George Lakoff",
		"playful parenting an exciting new approach to raising children that will help you nurture close connections solve behavior problems and encourage confidence": "Lawrence J. Cohen",
		"prisoners of geography": "Tim Marshall",
		"range": "David Epstein",
		"rework": "Jason Fried, David Heinemeier Hansson",
		"scale": "Geoffrey West",
		"schadenfreude": "Tiffany Watt Smith",
		"simplicity parenting": "Kim John Payne",
		"sludge": "Cass R. Sunstein",
		"strengthsfinder 20": "Tom Rath",
		"surely youre joking mr feynman": "Richard P. Feynman",
		"technotrends": "Daniel Burrus",
		"the 7 habits of highly effective people": "Stephen R. Covey",
		"the amazing generation": "Jonathan Haidt and Catherine Price",
		"the amazing teenage brain": "Nicola Morgan",
		"the art cure": "Daisy Fancourt",
		"the art of doing science and engineering": "Richard Hamming",
		"the art of innovation": "Tom Kelley",
		"the long tail why the future of business is selling less of more": "Chris Anderson",
		"the art of possibility": "Rosamund Stone Zander, Benjamin Zander",
		"the art of spending money": "Morgan Housel",
		"the art of travel": "Alain De Botton",
		"the art of uncertainty": "David Spiegelhalter",
		"the art of war": "Sun Tzu",
		"the baby whisperer": "Tracy Hogg, Melinda Blau",
		"the book you wish your parents had read": "Philippa Perry",
		"the clock of the long now": "Stewart Brand",
		"the computing universe": "Tony Hey, Gyuri Pápay",
		"the design of everyday things": "Donald A. Norman",
		"the elements of eloquence": "Mark Forsyth",
		"the elements of style": "Strunk and White",
		"the failure of risk management why its broken and how to fix it": "Douglas W. Hubbard",
		"the house at pooh corner": "A. A. Milne, Ernest H. Shepard",
		"the hunger games": "Suzanne Collins",
		"the new quantum universe": "Tony Hey, Patrick Walters",
		"the paula principle why women lose out at work and what needs to be done about it": "Tom Schuller",
		"the peter principle why things always go wrong": "Raymond Hull, Laurence J. Peter",
		"the practice of creativity": "George Prince",
		"the pragmatic programmer": "David Thomas, Andrew Hunt",
		"the presentation of self in everyday life": "Erving Goffman",
		"the prophet": "Kahlil Gibran",
		"the psychology of hope you can get there from here": "C. R. Snyder",
		"the pyramid principle": "Barbara Minto",
		"the shallows": "Nicholas G. Carr",
		"the tao of pooh": "Benjamin Hoff, Ernest H. Shepard",
		"things a little bird told me": "Biz Stone",
		"think and grow rich": "Napoleon Hill, Arthur R. Pell",
		"thinking fast and slow": "Daniel Kahneman",
		"this is your mind on plants": "Michael Pollan",
		"turn the ship around a true story of turning followers into leaders": "L. David Marquet, Stephen R. Covey",
		"ultra": "Brendan Leonard",
		"ultrasomething": "Brendan Leonard",
		"unconditional parenting": "Alfie Kohn",
		"user story mapping": "Jeff Patton",
		"wabi sabi simple": "Richard R. Powell",
		"water logic": "Edward de Bono",
		"what can you stack on the back of a yak": "Alison Green",
		"when the scientific secrets of perfect timing": "Daniel H. Pink",
		"when we were very young": "A. A. Milne, E. H Shephard",
		"william poundstones priceless the myth of fair value and how to take advantage of it": "William Poundstone",
		"winniethepooh": "A. A. Milne, Ernest H. Shepard",
		"wooden a lifetime of observations and reflections on and off the court": "John Wooden and Steve Jamison",
		"word perfect etymological entertainment every day": "Susie Dent"
	}
}
